zibo/__init__.py
zibo-0.0.1.dist-info/METADATA
zibo-0.0.1.dist-info/WHEEL
zibo-0.0.1.dist-info/top_level.txt
zibo-0.0.1.dist-info/RECORD
