Metadata-Version: 2.4
Name: zibo
Version: 0.0.1
Summary: Dummy lock package for zibo
Author: AutoPublisher
